google_drive/__init__.py
google_drive/gdrive.py
emo_google_drive-0.0.6.dist-info/LICENSE
emo_google_drive-0.0.6.dist-info/METADATA
emo_google_drive-0.0.6.dist-info/WHEEL
emo_google_drive-0.0.6.dist-info/top_level.txt
emo_google_drive-0.0.6.dist-info/RECORD
