Metadata-Version: 2.1
Name: emo_google_drive
Version: 0.0.6
Summary: Google Drive'da klasör oluşturma, dosya yükleme ve dosya indirme işlemlerini yöneten modül
Home-page: https://github.com/erenmustafaozdal/cache-db
Author: Eren Mustafa Özdal
Author-email: eren.060737@gmail.com
License: MIT
Requires-Python: >=3.11
License-File: LICENSE
Requires-Dist: pydrive
Requires-Dist: emo-file-system
